coldfront/__init__.py
coldfront/config/__init__.py
coldfront/config/auth.py
coldfront/config/base.py
coldfront/config/core.py
coldfront/config/database.py
coldfront/config/email.py
coldfront/config/env.py
coldfront/config/logging.py
coldfront/config/settings.py
coldfront/config/urls.py
coldfront/config/wsgi.py
coldfront/config/plugins/__init__.py
coldfront/config/plugins/api.py
coldfront/config/plugins/auto_compute_allocation.py
coldfront/config/plugins/freeipa.py
coldfront/config/plugins/iquota.py
coldfront/config/plugins/ldap.py
coldfront/config/plugins/ldap_user_search.py
coldfront/config/plugins/openid.py
coldfront/config/plugins/project_openldap.py
coldfront/config/plugins/slurm.py
coldfront/config/plugins/system_monitor.py
coldfront/config/plugins/xdmod.py
coldfront/core/__init__.py
coldfront/core/attribute_expansion.py
coldfront/core/allocation/__init__.py
coldfront/core/allocation/admin.py
coldfront/core/allocation/apps.py
coldfront/core/allocation/forms.py
coldfront/core/allocation/models.py
coldfront/core/allocation/signals.py
coldfront/core/allocation/tasks.py
coldfront/core/allocation/urls.py
coldfront/core/allocation/utils.py
coldfront/core/allocation/views.py
coldfront/core/allocation/management/__init__.py
coldfront/core/allocation/management/commands/__init__.py
coldfront/core/allocation/management/commands/add_allocation_defaults.py
coldfront/core/allocation/management/commands/enable_change_requests_globally.py
coldfront/core/allocation/migrations/0001_initial.py
coldfront/core/allocation/migrations/0002_auto_20190718_1451.py
coldfront/core/allocation/migrations/0003_auto_20191018_1049.py
coldfront/core/allocation/migrations/0004_auto_20211102_1017.py
coldfront/core/allocation/migrations/0005_auto_20211117_1413.py
coldfront/core/allocation/migrations/__init__.py
coldfront/core/allocation/templates/allocation/allocation_account_list.html
coldfront/core/allocation/templates/allocation/allocation_add_invoice_note.html
coldfront-1.1.7.dist-info/METADATA
coldfront-1.1.7.dist-info/WHEEL
coldfront-1.1.7.dist-info/entry_points.txt
coldfront-1.1.7.dist-info/licenses/LICENSES/AGPL-3.0-or-later.txt
coldfront-1.1.7.dist-info/licenses/LICENSES/CC-BY-NC-ND-4.0.txt
coldfront-1.1.7.dist-info/licenses/LICENSES/CC0-1.0.txt
coldfront-1.1.7.dist-info/licenses/LICENSES/ISC.txt
coldfront-1.1.7.dist-info/licenses/LICENSES/MIT.txt
coldfront-1.1.7.dist-info/RECORD
