Metadata-Version: 2.4
Name: coldfront
Version: 1.1.7
Summary: HPC Resource Allocation System
Project-URL: Bug Tracker, https://github.com/ubccr/coldfront/issues
Project-URL: Changelog, https://github.com/ubccr/coldfront/blob/main/CHANGELOG.md
Project-URL: Documentation, https://coldfront.readthedocs.io
Project-URL: Source Code, https://github.com/ubccr/coldfront
Author: Andrew E. Bruno, Dori Sajdak, Mohammad Zia
License-Expression: AGPL-3.0-or-later
License-File: LICENSES/AGPL-3.0-or-later.txt
License-File: LICENSES/CC-BY-NC-ND-4.0.txt
License-File: LICENSES/CC0-1.0.txt
License-File: LICENSES/ISC.txt
License-File: LICENSES/MIT.txt
Keywords: high-performance-computing,resource-allocation
Classifier: Framework :: Django :: 4.2
Classifier: Programming Language :: Python :: 3
Classifier: Topic :: Internet :: WWW/HTTP :: WSGI :: Application
Classifier: Topic :: Scientific/Engineering
Classifier: Topic :: System :: Systems Administration
Requires-Python: >=3.9
Requires-Dist: crispy-bootstrap4>=2024.10
Requires-Dist: django-crispy-forms>=2.3
Requires-Dist: django-environ>=0.12.0
Requires-Dist: django-filter>=25.1
Requires-Dist: django-model-utils>=5.0.0
Requires-Dist: django-q2>=1.7.6
Requires-Dist: django-settings-export>=1.2.1
Requires-Dist: django-simple-history>=3.8.0
Requires-Dist: django-split-settings>=1.3.2
Requires-Dist: django-su>=1.0.0
Requires-Dist: django<5,>4.2
Requires-Dist: djangorestframework>=3.16.0
Requires-Dist: doi2bib>=0.4.0
Requires-Dist: fontawesome-free>=5.15.4
Requires-Dist: formencode>=2.1.1
Requires-Dist: gunicorn>=23.0.0
Requires-Dist: humanize>=4.12.2
Requires-Dist: python-dateutil>=2.9.0.post0
Requires-Dist: redis>=5.2.1
Provides-Extra: freeipa
Requires-Dist: dbus-python>=1.4.0; extra == 'freeipa'
Requires-Dist: ipaclient>=4.12.2; extra == 'freeipa'
Provides-Extra: iquota
Requires-Dist: kerberos>=1.3.1; extra == 'iquota'
Provides-Extra: ldap
Requires-Dist: django-auth-ldap>=5.1.0; extra == 'ldap'
Requires-Dist: ldap3>=2.9.1; extra == 'ldap'
Provides-Extra: mysql
Requires-Dist: mysqlclient>=2.2.7; extra == 'mysql'
Provides-Extra: oidc
Requires-Dist: mozilla-django-oidc>=4.0.1; extra == 'oidc'
Provides-Extra: pg
Requires-Dist: psycopg2>=2.9.10; extra == 'pg'
